LICENCE
README.md
setup.py
lib/sip_models/__init__.py
lib/sip_models/plot_helper.py
lib/sip_models/sip_response.py
lib/sip_models/units.py
lib/sip_models.egg-info/PKG-INFO
lib/sip_models.egg-info/SOURCES.txt
lib/sip_models.egg-info/dependency_links.txt
lib/sip_models.egg-info/requires.txt
lib/sip_models.egg-info/top_level.txt
lib/sip_models/cond/__init__.py
lib/sip_models/cond/cc.py
lib/sip_models/res/__init__.py
lib/sip_models/res/cc.py
test/test.py
tests/test_res.py